dartrs-0.1.5.dist-info/METADATA
dartrs-0.1.5.dist-info/WHEEL
dartrs-0.1.5.dist-info/license_files/LICENSE
dartrs/py.typed
dartrs/__init__.py
dartrs/utils.py
dartrs/v2.py
dartrs/dartrs.pyi
dartrs/dartrs.cpython-38-s390x-linux-gnu.so
dartrs-0.1.5.dist-info/RECORD
